twitter.common.decorators-0.3.11-py2.7-nspkg.pth
twitter/common/decorators/__init__.py
twitter/common/decorators/lru_cache.py
twitter/common/decorators/threads.py
twitter.common.decorators-0.3.11.dist-info/DESCRIPTION.rst
twitter.common.decorators-0.3.11.dist-info/METADATA
twitter.common.decorators-0.3.11.dist-info/RECORD
twitter.common.decorators-0.3.11.dist-info/WHEEL
twitter.common.decorators-0.3.11.dist-info/metadata.json
twitter.common.decorators-0.3.11.dist-info/namespace_packages.txt
twitter.common.decorators-0.3.11.dist-info/top_level.txt
twitter.common.decorators-0.3.11.dist-info/zip-safe
